{
  "project_info": {
    "project_number": "33025951778",
    "project_id": "medicatch-c7cfc",
    "storage_bucket": "medicatch-c7cfc.firebasestorage.app"
  },
  "client": [
    {
      "client_info": {
        "mobilesdk_app_id": "1:33025951778:android:c7a8fb94336079bd2a627b",
        "android_client_info": {
          "package_name": "dev.expo.Medicatch_with_js"
        }
      },
      "oauth_client": [],
      "api_key": [
        {
          "current_key": "AIzaSyCLnSf1QXJ3kUKIyeyv7B8hAl4fgvs_ktI"
        }
      ],
      "services": {
        "appinvite_service": {
          "other_platform_oauth_client": []
        }
      }
    }
  ],
  "configuration_version": "1"
}